nilm_analyzer/__init__.py
nilm_analyzer/loaders.py
nilm_analyzer/utilities.py
nilm_analyzer/metadata/__init__.py
nilm_analyzer/metadata/ampds/__init__.py
nilm_analyzer/metadata/ampds/building1.yaml
nilm_analyzer/metadata/deddiag/__init__.py
nilm_analyzer/metadata/deddiag/house_00.tsv
nilm_analyzer/metadata/deddiag/house_01.tsv
nilm_analyzer/metadata/deddiag/house_02.tsv
nilm_analyzer/metadata/deddiag/house_03.tsv
nilm_analyzer/metadata/deddiag/house_04.tsv
nilm_analyzer/metadata/deddiag/house_05.tsv
nilm_analyzer/metadata/deddiag/house_06.tsv
nilm_analyzer/metadata/deddiag/house_07.tsv
nilm_analyzer/metadata/deddiag/house_08.tsv
nilm_analyzer/metadata/deddiag/house_09.tsv
nilm_analyzer/metadata/deddiag/house_10.tsv
nilm_analyzer/metadata/deddiag/house_11.tsv
nilm_analyzer/metadata/deddiag/house_12.tsv
nilm_analyzer/metadata/deddiag/house_13.tsv
nilm_analyzer/metadata/deddiag/house_14.tsv
nilm_analyzer/metadata/gelap/__init__.py
nilm_analyzer/metadata/gelap/hh-01/__init__.py
nilm_analyzer/metadata/gelap/hh-01/info.json
nilm_analyzer/metadata/gelap/hh-02/__init__.py
nilm_analyzer/metadata/gelap/hh-02/info.json
nilm_analyzer/metadata/gelap/hh-03/__init__.py
nilm_analyzer/metadata/gelap/hh-03/info.json
nilm_analyzer/metadata/gelap/hh-04/__init__.py
nilm_analyzer/metadata/gelap/hh-04/info.json
nilm_analyzer/metadata/gelap/hh-05/__init__.py
nilm_analyzer/metadata/gelap/hh-05/info.json
nilm_analyzer/metadata/gelap/hh-06/__init__.py
nilm_analyzer/metadata/gelap/hh-06/info.json
nilm_analyzer/metadata/gelap/hh-07/__init__.py
nilm_analyzer/metadata/gelap/hh-07/info.json
nilm_analyzer/metadata/gelap/hh-08/__init__.py
nilm_analyzer/metadata/gelap/hh-08/info.json
nilm_analyzer/metadata/gelap/hh-09/__init__.py
nilm_analyzer/metadata/gelap/hh-09/info.json
nilm_analyzer/metadata/gelap/hh-10/__init__.py
nilm_analyzer/metadata/gelap/hh-10/info.json
nilm_analyzer/metadata/gelap/hh-11/__init__.py
nilm_analyzer/metadata/gelap/hh-11/info.json
nilm_analyzer-1.0.11.dist-info/LICENSE
nilm_analyzer-1.0.11.dist-info/METADATA
nilm_analyzer-1.0.11.dist-info/WHEEL
nilm_analyzer-1.0.11.dist-info/top_level.txt
nilm_analyzer-1.0.11.dist-info/RECORD
