Metadata-Version: 2.1
Name: nilm-analyzer
Version: 1.0.11
Summary: A simple python package for easy loading and manipulation of NILM datasets.
Author-email: Mahnoor Shahid <mahnoor.shahid.shakir@outlook.com>
License: MIT License
Project-URL: repository, https://github.com/mahnoor-shahid/nilm_analyzer
Classifier: Programming Language :: Python :: 3
Classifier: License :: OSI Approved :: MIT License
Classifier: Operating System :: OS Independent
Requires-Python: >=3.9.2
License-File: LICENSE
Requires-Dist: numpy (>=1.20.3)
Requires-Dist: pandas (>=1.2.4)
Requires-Dist: dask (>=2021.06.2)
Requires-Dist: scikit-learn (>=1.1.2)
